kni/__init__.py
knij-1.0.1.dist-info/LICENSE.md
knij-1.0.1.dist-info/METADATA
knij-1.0.1.dist-info/WHEEL
knij-1.0.1.dist-info/top_level.txt
knij-1.0.1.dist-info/RECORD
