Metadata-Version: 2.1
Name: knij
Version: 1.0.1
Summary: KAMAR Notices Interface - A way to access notices from KAMAR in a bunch of languages (Python)
Home-page: https://github.com/jacobtread/KNI-Py
Author: Jacobtread
Author-email: jacobtread@gmail.com
License: UNKNOWN
Platform: UNKNOWN
Classifier: Programming Language :: Python :: 3
Classifier: License :: OSI Approved :: MIT License
Classifier: Operating System :: OS Independent
Requires-Python: >=3.8
